{
    "version": "https://jsonfeed.org/version/1",
    "title": "大蛋糕的烘焙坊",
    "home_page_url": "https://lihaoyu.cn/",
    "feed_url": "https://lihaoyu.cn/feed.json",
    "description": "一个屑初三学生的小窝",
    "icon": "https://img-blog.csdnimg.cn/5f3a26e6ee01493f9373a38633e5f2df.webp",
    "author": {
        "name": "Big_Cake",
        "url": "https://valaxy.site"
    },
    "items": [
        {
            "id": "",
            "content_html": "<p>不请自来。</p>\n<p>本人是一位普通的 Minecraft 国际版玩家，也是一位 BakaXL 用户。</p>\n<p>如大家所见，2 月 5 日在知乎上发布的那个问题就是我提出的。</p>\n<p>给不知道的人一个传送门：<a href=\"https://www.zhihu.com/question/582313498\">https://www.zhihu.com/question/582313498</a></p>\n<p>昨天晚上，我在 B 站上刷到了这一篇文章，认为该文章中有诸多地方不合理，故在此发布该专栏进行说明。</p>\n",
            "url": "https://lihaoyu.cn/posts/my-opinions-about-that-post",
            "title": "Minecraft 国际版玩家对近期事件的回应",
            "date_modified": "2023-02-12T15:59:59.000Z",
            "date_published": "2023-02-18T15:54:16.000Z",
            "author": {
                "name": "Big_Cake",
                "url": "https://valaxy.site"
            }
        },
        {
            "id": "",
            "content_html": "<p>开学后的第一更。</p>\n<p>网易，你觉得你对得起你那“游戏热爱者”的口号吗？</p>\n",
            "url": "https://lihaoyu.cn/posts/netease-and-minecraft",
            "title": "对网易与 Minecraft 国际版的担忧",
            "date_modified": "2023-02-11T20:30:59.000Z",
            "date_published": "2023-02-18T15:54:16.000Z",
            "author": {
                "name": "Big_Cake",
                "url": "https://valaxy.site"
            }
        },
        {
            "id": "",
            "content_html": "<p>以前我提到过，我很喜欢 UWP 应用，因为大多数 UWP 的界面都能与 Windows 完美融合在一起。</p>\n<p>前段时间因为网易云音乐官方的客户端不合我意，以及它的资源占用，我便尝试寻找一个第三方的网易云音乐客户端。</p>\n<p>正好在 B 站上看到了 LyricEase 复活的视频，以前也对 LyricEase 有所耳闻，便决定拿来用。</p>\n<p>用了少说也有半个月了，是时候宣传出去了。</p>\n",
            "url": "https://lihaoyu.cn/posts/lyricease",
            "title": "诈尸？—— 第三方网易云音乐客户端 LyricEase",
            "date_modified": "2023-01-08T13:07:43.000Z",
            "date_published": "2023-02-01T11:05:20.000Z",
            "author": {
                "name": "Big_Cake",
                "url": "https://valaxy.site"
            }
        },
        {
            "id": "",
            "content_html": "<h2>声明</h2>\n<p><strong>首先说明：我坚定的支持“一国两制”，坚决反对一切分裂国家、破坏统一的行为。任何邪恶，终将被绳之以法！</strong></p>\n<h2>前言</h2>\n<blockquote>\n<p>本文在 Windows 11 + Ubuntu 双系统</p>\n</blockquote>\n",
            "url": "https://lihaoyu.cn/posts/goodbye-npp",
            "title": "再见，Notepad++",
            "date_modified": "2023-01-28T14:08:24.000Z",
            "date_published": "2023-01-28T14:08:24.000Z",
            "author": {
                "name": "Big_Cake",
                "url": "https://valaxy.site"
            }
        },
        {
            "id": "",
            "content_html": "<p>隆重向您介绍 BakaXL！全新的 BakaXL 3.0 版本为各位带来了更直观的本体设置界面、全新装修过的笨蛋广场、更丰富多彩的个性化选项、更快速的核心安装，以及对 Modrinth 的完整支持！</p>\n",
            "url": "https://lihaoyu.cn/posts/bakaxl-launcher",
            "title": "你的下一个启动器，何必是启动器",
            "date_modified": "2023-01-16T12:19:47.000Z",
            "date_published": "2023-01-16T12:19:47.000Z",
            "author": {
                "name": "Big_Cake",
                "url": "https://valaxy.site"
            }
        },
        {
            "id": "",
            "content_html": "<h2>前言</h2>\n<p>其实我已经关注云游君的 <a href=\"https://valaxy.site\">Valaxy</a> 很久了，无奈没有条件只能一直用 Hexo。</p>\n<p>最近上网课拿到电脑，便想着“不然把博客迁移到 Valaxy 吧”，便打开了 Valaxy 的文档开始一顿操作，设置好以后已经基本处于可以用在生产环境的情况了。</p>\n<p>同时我也感受到了它超快的速度以及原生的页面热重载，便打算把它介绍给大家。</p>\n",
            "url": "https://lihaoyu.cn/posts/valaxy",
            "title": "Valaxy —— 快到没边的全新静态博客框架",
            "date_modified": "2022-10-17T08:35:47.000Z",
            "date_published": "2022-10-17T08:35:47.000Z",
            "author": {
                "name": "Big_Cake",
                "url": "https://valaxy.site"
            }
        },
        {
            "id": "",
            "content_html": "<p>近几天在群里聊天，发现几乎每个群都在传 Chrome 翻译用不了了和竹新社的新闻，一搜才知道原来谷歌把国内的翻译服务 <a href=\"http://translate.google.cn\">translate.google.cn</a> 停止了。理由是“低使用率”。</p>\n<blockquote>\n<p>*根据</p>\n</blockquote>\n",
            "url": "https://lihaoyu.cn/posts/google-translate-unavailable",
            "title": "见证历史了——谷歌取消大陆地区翻译服务",
            "date_modified": "2022-10-02T18:40:35.000Z",
            "date_published": "2022-10-02T19:53:24.000Z",
            "author": {
                "name": "Big_Cake",
                "url": "https://valaxy.site"
            }
        },
        {
            "id": "",
            "content_html": "<p>emmmm，这个 App 我是在暑假的时候看到的。</p>\n<p>当时我在刷 B 站，忽然间就看到了这个 App 的作者发布的视频。</p>\n<p>虽然当时的版本很简陋，但是因为当时米游社还没有实装实时便签小组件，而我的确有这种需求，便装了一个。</p>\n",
            "url": "https://lihaoyu.cn/posts/genshin-pizza-helper",
            "title": "在 iOS 桌面查看你的原神账号信息——原神披萨小助手",
            "date_modified": "2022-09-10T20:36:27.000Z",
            "date_published": "2022-09-10T20:36:27.000Z",
            "author": {
                "name": "Big_Cake",
                "url": "https://valaxy.site"
            }
        },
        {
            "id": "",
            "content_html": "<h2>前言</h2>\n<p>(｡･∀･)ﾉﾞ嗨，各位老爷们大家好！</p>\n<p>先祝贺大家 <s>PHP Fatal Error</s> 中秋节快乐！</p>\n<p>如大家所见，我已经开学了，我也真正成为了一名初三年级的学生。</p>\n<p>放假三天，这是我开学后第一次更新文章。这三天我打算给博客再做点事情，以及日常维护。</p>\n<p>不知不觉中，时间就溜走了，2022 也即将成为历史。这一年来我做了哪些过意不去的事情也需要自己思考一下了。</p>\n<p><img src=\"https://img-blog.csdnimg.cn/b9158fb2fffd4cd883966614fb7de835.webp\" alt=\"calendar\"></p>\n<p>终于要迎来第一篇年终回顾了呢，心情有点复杂......</p>\n<p>接下来，我要开始介绍这个部落格在未来一段时间内的计划了。</p>\n",
            "url": "https://lihaoyu.cn/posts/happy-mid-autumn-festival",
            "title": "中秋节快乐！以及一些碎碎念",
            "date_modified": "2022-09-10T19:18:49.000Z",
            "date_published": "2022-09-10T19:18:49.000Z",
            "author": {
                "name": "Big_Cake",
                "url": "https://valaxy.site"
            }
        },
        {
            "id": "",
            "content_html": "<h2>前言</h2>\n<p><s>这年头连启动器都开始卷了</s></p>\n<p>从最开始的 PCL2，到现在的 BakaXL、HMCL、FSM3，它们都相继支持了联机。</p>\n<p>但是这个体验嘛，就可能天上地下了。</p>\n<p>目前在我用过的所有支持联机的启动器里，BakaXL 的体验可以说是最好的了。毕竟完全免费的中继、正版盗版随意联机和友好的失败原因提示摆在那里。</p>\n<p>正因如此，本文将使用 BakaXL 进行演示。</p>\n",
            "url": "https://lihaoyu.cn/posts/play-minecraft-with-friends",
            "title": "与朋友联机游玩 Minecraft",
            "date_modified": "2022-08-22T15:45:05.000Z",
            "date_published": "2022-08-22T15:45:05.000Z",
            "author": {
                "name": "Big_Cake",
                "url": "https://valaxy.site"
            }
        },
        {
            "id": "",
            "content_html": "<h2>前言</h2>\n<p>有没有一种可能，大家当中的一部分人都在为自己的网站速度而苦恼呢？</p>\n<p>特别是去年 12 月 jsDelivr 的备案被吊销以后，很多网站的速度明显下降。</p>\n<p>这篇文章，我会把我的经验分享给大家，希望能对各位的情况有点作用。</p>\n",
            "url": "https://lihaoyu.cn/posts/site-speed-optimization",
            "title": "优化站点速度之见解",
            "date_modified": "2022-07-15T13:32:45.000Z",
            "date_published": "2022-07-15T13:32:45.000Z",
            "author": {
                "name": "Big_Cake",
                "url": "https://valaxy.site"
            }
        },
        {
            "id": "",
            "content_html": "<h2>前言</h2>\n<p>其实在这之前我一直用的是网上公开的加速 IP，比如 NoCheatPlus 团队的公益加速 IP。</p>\n<p>然而昨天这个加速 IP 出了点问题，Minecraft 连不上去了。</p>\n<p>我就想，要不然自己搭建一个算了，稳定还省心呢。</p>\n<p>于是这篇文章应运而生。</p>\n",
            "url": "https://lihaoyu.cn/posts/build-hypixel-boost-ip",
            "title": "搭建 Hypixel 加速 IP",
            "date_modified": "2022-07-13T16:48:21.000Z",
            "date_published": "2022-07-13T16:48:21.000Z",
            "author": {
                "name": "Big_Cake",
                "url": "https://valaxy.site"
            }
        },
        {
            "id": "",
            "content_html": "<h2>前言</h2>\n<p>可能大家用 VuePress 做文档的已经厌烦了每天对着终端敲 <code>yarn docs:build</code> 了吧。</p>\n<p>想用 CI 却苦于配置无从下手。</p>\n<p>这里我来和大家分享一下，如何将 VuePress 文档部署到 Vercel 上。</p>\n",
            "url": "https://lihaoyu.cn/posts/deploy-vuepress-v1-docs-to-vercel",
            "title": "部署 VuePress v1 文档到 Vercel",
            "date_modified": "2022-07-10T08:43:54.000Z",
            "date_published": "2022-07-10T08:43:54.000Z",
            "author": {
                "name": "Big_Cake",
                "url": "https://valaxy.site"
            }
        },
        {
            "id": "",
            "content_html": "<h2>Hexo</h2>\n<p>Welcome to Hexo! This is your very first post. Check documentation for more info. If you get any problems when using Hexo, you can find the answer in troubleshooting or you can ask me on GitHub.</p>\n",
            "url": "https://lihaoyu.cn/posts/hello-world",
            "title": "Hello World!",
            "date_modified": "2022-07-08T12:57:47.000Z",
            "date_published": "2022-07-08T12:57:47.000Z",
            "author": {
                "name": "Big_Cake",
                "url": "https://valaxy.site"
            }
        },
        {
            "id": "",
            "content_html": "<h2>前言</h2>\n<p>其实 Backblaze 这个东西我今年初才听说，当时我疯狂的在网上搜可以白嫖的对象存储。</p>\n<p>然后我就看到了 Backblaze B2，免费 10GB 对象存储 + 每天免费 1GB 下载流量。</p>\n<blockquote>\n<p>感觉挺香的，你们觉得呢（</p>\n</blockquote>\n",
            "url": "https://lihaoyu.cn/posts/backblaze-b2",
            "title": "白嫖党福利——Backblaze B2 免费 10GB 对象存储",
            "date_modified": "2022-07-07T21:53:31.000Z",
            "date_published": "2022-07-07T21:53:31.000Z",
            "author": {
                "name": "Big_Cake",
                "url": "https://valaxy.site"
            }
        },
        {
            "id": "",
            "content_html": "<h2>前言</h2>\n<p>Windows 的更新下载速度那是真的慢（虽然比官网下镜像快多了）。</p>\n<p>Windows 10 发布的时候，传递优化伴随着它一同出现在人们眼前。</p>\n<p>这应该是 <s>M$</s> 为了进一步改善更新下载速度而做出来的东西吧。</p>\n",
            "url": "https://lihaoyu.cn/posts/windows-delievry-optimize",
            "title": "打开 Windows 传递优化，利人利己！",
            "date_modified": "2022-07-05T19:50:21.000Z",
            "date_published": "2022-07-05T19:50:21.000Z",
            "author": {
                "name": "Big_Cake",
                "url": "https://valaxy.site"
            }
        },
        {
            "id": "",
            "content_html": "<h2>前言</h2>\n<p>Windows Search 这个东西，一言难尽......</p>\n<p>你说它没用吧，它还挺有用的；你说它有用吧，它搜索速度还贼慢，还搜不到想要的东西。</p>\n<p>这篇文章，我会告诉各位我的 Windows 搜索为什么那么好用，以及该怎么进行配置。</p>\n",
            "url": "https://lihaoyu.cn/posts/windows-search-optimization",
            "title": "优化 Windows Search 搜索，加快搜索速度！",
            "date_modified": "2022-07-04T16:18:16.000Z",
            "date_published": "2022-07-04T16:18:16.000Z",
            "author": {
                "name": "Big_Cake",
                "url": "https://valaxy.site"
            }
        },
        {
            "id": "",
            "content_html": "<p>好的，又是一篇新的文章！其实网上的教程够多了，基本都能达到目标。</p>\n<p>但是我要写一个简单的教程来取代它们（其实如果自己忘了也可以看看）</p>\n<p>废话少说，让我们开始吧！</p>\n<blockquote>\n<p>前排提示：本教程仅适用于 Min</p>\n</blockquote>\n",
            "url": "https://lihaoyu.cn/posts/build-your-minecraft-server",
            "title": "搭建一个属于你自己的 Minecraft 服务器",
            "date_modified": "2022-04-09T21:58:44.000Z",
            "date_published": "2022-04-09T21:58:44.000Z",
            "author": {
                "name": "Big_Cake",
                "url": "https://valaxy.site"
            }
        },
        {
            "id": "",
            "content_html": "<h2>前言</h2>\n<p>妈耶，终于修好 Hexo 报 YAMLException 的问题了，上次更新已经是 5 个月前了呢！</p>\n<p>这段时间没更新，主要就是 Hexo 的锅。</p>\n<blockquote>\n<p>顺带一提，又回归到网课时期了（我这边有疫情）</p>\n</blockquote>\n<p>由于 <s>Mojang</s> Bugjump 的传统艺能，Minecraft Java 版通常会因为各种玄幻的原因崩溃，这篇文章将会带着你判断你的 Minecraft 出了什么问题，以及可能的修复方法。</p>\n",
            "url": "https://lihaoyu.cn/posts/minecraft-problems-solve",
            "title": "如何诊断 Minecraft Java 版客户端中的错误",
            "date_modified": "2022-04-08T07:45:18.000Z",
            "date_published": "2022-04-08T07:45:18.000Z",
            "author": {
                "name": "Big_Cake",
                "url": "https://valaxy.site"
            }
        },
        {
            "id": "",
            "content_html": "<p><img src=\"https://img.shields.io/github/issues-pr/Big-Cake-jpg/Cake-Launcher?label=Pull%20Requests&amp;style=flat-square\" alt=\"GitHub pull requests\"><img src=\"https://img.shields.io/github/issues/Big-Cake-jpg/Cake-Launcher?label=Issues&amp;style=flat-square\" alt=\"GitHub issues\"><img src=\"https://img.shields.io/github/license/Big-Cake-jpg/Cake-Launcher?label=License&amp;style=flat-square\" alt=\"GitHub\"><img src=\"https://img.shields.io/github/repo-size/Big-Cake-jpg/Cake-Launcher?label=Repository%20Size&amp;style=flat-square\" alt=\"GitHub repo size\"><img src=\"https://img.shields.io/github/contributors/Big-Cake-jpg/Cake-Launcher?label=Contributors&amp;style=flat-square\" alt=\"GitHub contributors\"><img src=\"https://img.shields.io/github/last-commit/Big-Cake-jpg/Cake-Launcher?label=Last%20commit&amp;style=flat-square\" alt=\"GitHub last commit\"><img src=\"https://img.shields.io/badge/Author-Big__Cake-blue?style=flat-square\" alt=\"GitHub Author\"><img src=\"https://img.shields.io/github/stars/Big-Cake-jpg/Cake-Launcher?label=Stars&amp;style=flat-square\" alt=\"GitHub Repo stars\"><img src=\"https://img.shields.io/github/forks/Big-Cake-jpg/Cake-Launcher?label=Forks&amp;style=flat-square\" alt=\"GitHub forks\"></p>\n<p><a href=\"https://github.com/Big-Cake-jpg/Cake-Launcher\">Cake Launcher</a> 是我为自己的 Minecraft 服务器开发的一个启动器 <s>（蛋糕启动器（误））</s></p>\n",
            "url": "https://lihaoyu.cn/posts/launcher-develop",
            "title": "Cake Launcher 开发日志",
            "date_modified": "2021-09-30T16:49:20.000Z",
            "date_published": "2022-04-07T20:53:19.000Z",
            "author": {
                "name": "Big_Cake",
                "url": "https://valaxy.site"
            }
        },
        {
            "id": "",
            "content_html": "<blockquote>\n<p>写给一个想要拥有自己的博客，却没有资金的小白和小学时的自己</p>\n</blockquote>\n<h2>前言</h2>\n<p>虽然，独立博客的时代已经过去，越来越多的人们开始在大平台上发布自己的文章</p>\n<p>虽然，这些平台的流量能够为这些博主们创造收</p>\n",
            "url": "https://lihaoyu.cn/posts/build-a-hexo-blog",
            "title": "手把手教你如何搭建属于自己的 Hexo 博客",
            "date_modified": "2021-12-04T16:45:10.000Z",
            "date_published": "2021-12-04T16:45:10.000Z",
            "author": {
                "name": "Big_Cake",
                "url": "https://valaxy.site"
            }
        },
        {
            "id": "",
            "content_html": "<blockquote>\n<p>《关于加个引号就能变成小说这件事》</p>\n</blockquote>\n<h2>前言</h2>\n<p>说实话，这件事情本来能避免的，只是因为我当时~脑子抽了~上物理课的时候写地理默写</p>\n<p>结果就有了下面的这件事情......</p>\n",
            "url": "https://lihaoyu.cn/posts/a-little-teacher",
            "title": "关于我讲了节物理课这件事",
            "date_modified": "2021-12-03T01:07:23.000Z",
            "date_published": "2021-12-03T01:07:23.000Z",
            "author": {
                "name": "Big_Cake",
                "url": "https://valaxy.site"
            }
        },
        {
            "id": "",
            "content_html": "<h2>前言</h2>\n<p>CakeMC 是我自己的一个 Minecraft 服务器，早在 Cake Launcher 的开发日志里就有提到</p>\n<p>它于今年 8 月份开始运营，到现在已经获得了较多的玩家数量，最高日在线数量达到了 6-7 人</p>\n<p>这对于一个没有多少宣传、新运营的服务器来说已经很不错了</p>\n<p>目前它甚至还获得了他人的帮助（指免费挂的面板服）</p>\n<p>下面开始正文……</p>\n",
            "url": "https://lihaoyu.cn/posts/my-mcserver",
            "title": "我的 Minecraft 服务器 —— CakeMC",
            "date_modified": "2021-10-03T14:01:12.000Z",
            "date_published": "2021-10-03T14:01:12.000Z",
            "author": {
                "name": "Big_Cake",
                "url": "https://valaxy.site"
            }
        },
        {
            "id": "",
            "content_html": "<p>今天，我在 Surfing the Internet 的时候往博客的 Aplayer 挂件里塞了个音乐列表</p>\n<p>结果发现 GitHub 突然无法访问了，显示 “连接超时”</p>\n<p>![GitHub-unacc</p>\n",
            "url": "https://lihaoyu.cn/posts/about-github-access",
            "title": "关于 GitHub 今年国庆节访问的问题",
            "date_modified": "2021-10-01T08:55:13.000Z",
            "date_published": "2021-10-01T08:55:13.000Z",
            "author": {
                "name": "Big_Cake",
                "url": "https://valaxy.site"
            }
        },
        {
            "id": "",
            "content_html": "<p>想必看到这篇文章的大家大部分都经常因为运行内存不够而头疼吧</p>\n<p>在这篇文章中，我将会为大家介绍这款软件 ——— <a href=\"https://henrypp.org/product/memreduct\">Mem Reduct</a></p>\n<hr>\n<h2>前言</h2>\n<p>任何优化软件都只能在一定程度上进行优化，有时甚至不会有什么效果</p>\n<p>因此如果你有“钞能力”，那我还是建议你给电脑加一根内存条</p>\n",
            "url": "https://lihaoyu.cn/posts/mem-reduct",
            "title": "神级内存清理软件———Mem Reduct",
            "date_modified": "2021-09-20T20:58:00.000Z",
            "date_published": "2021-09-20T20:58:00.000Z",
            "author": {
                "name": "Big_Cake",
                "url": "https://valaxy.site"
            }
        }
    ]
}